sankee/__init__.py
sankee/datasets.py
sankee/plotting.py
sankee/sampling.py
sankee/themes.py
sankee/utils.py
sankee-0.3.0.dist-info/METADATA
sankee-0.3.0.dist-info/WHEEL
sankee-0.3.0.dist-info/licenses/LICENSE
sankee-0.3.0.dist-info/RECORD
