Metadata-Version: 2.4
Name: sankee
Version: 0.3.0
Summary: Visualize classified time series data with interactive Sankey plots in Google Earth Engine.
Project-URL: Homepage, https://github.com/aazuspan/sankee
Project-URL: Source, https://github.com/aazuspan/sankee
Author-email: Aaron Zuspan <aazuspan@gmail.com>
License-Expression: MIT
License-File: LICENSE
Keywords: earth-engine,land-cover,sankey,visualization
Classifier: Development Status :: 4 - Beta
Classifier: Intended Audience :: Science/Research
Classifier: License :: OSI Approved :: MIT License
Classifier: Programming Language :: Python :: 3
Classifier: Programming Language :: Python :: 3.9
Classifier: Programming Language :: Python :: 3.10
Classifier: Programming Language :: Python :: 3.11
Classifier: Programming Language :: Python :: 3.12
Classifier: Topic :: Scientific/Engineering :: GIS
Requires-Python: >=3.9
Requires-Dist: earthengine-api>=0.1.230
Requires-Dist: ipywidgets
Requires-Dist: numpy
Requires-Dist: pandas
Requires-Dist: plotly<6.0,>=5.2.2
